image_processing2/__init__.py
image_processing2/processing/__init__.py
image_processing2/processing/combination.py
image_processing2/processing/transformation.py
image_processing2/utils/__init__.py
image_processing2/utils/io.py
image_processing2/utils/plot.py
image_processing2-0.0.2.dist-info/METADATA
image_processing2-0.0.2.dist-info/WHEEL
image_processing2-0.0.2.dist-info/top_level.txt
image_processing2-0.0.2.dist-info/RECORD
