Metadata-Version: 2.1
Name: image-processing2
Version: 0.0.2
Summary: My short description
Home-page: https://github.com/Davi-dev-C/package-template
Author: Davi H.
Author-email: davi.henrique.lima01@gmail.com
License: UNKNOWN
Platform: UNKNOWN
Requires-Python: >=3.8
